setup.py
brexcel/__init__.py
brexcel/rexcel.py
brexcel/wexcel.py
brexcel.egg-info/PKG-INFO
brexcel.egg-info/SOURCES.txt
brexcel.egg-info/dependency_links.txt
brexcel.egg-info/not-zip-safe
brexcel.egg-info/requires.txt
brexcel.egg-info/top_level.txt