Metadata-Version: 1.1
Name: brexcel
Version: 0.2
Summary: Converts excel to a python dict and vice-versa
Home-page: https://github.com/brunogoncalooliveira/brexcel
Author: Bruno Oliveira
Author-email: UNKNOWN
License: MIT
Keywords: excel dict convert xls xlsx
Platform: UNKNOWN
Classifier: Development Status :: 2 - Pre-Alpha
Classifier: License :: OSI Approved :: MIT License
Classifier: Programming Language :: Python :: 2.7
Classifier: Topic :: Text Processing :: Linguistic
